[
 {
  "date": "Mon, 29 May 2017 12:00:03 +0000", 
  "link": "http://www.ifanr.com/844943?utm_source=rss&utm_medium=rss&utm_campaign=", 
  "description": "敲黑板：以后说到 ARM 的处理器架构该更新了<p>#欢迎关注爱范儿官方微信公众号：爱范儿（微信号：ifanr），更多精彩内容第一时间为您奉上。</p><p>\n<a href=\"http://www.ifanr.com\">爱范儿</a> |\n<a href=\"http://www.ifanr.com/844943\">原文链接</a> ·\n<a href=\"http://www.ifanr.com/844943#comments\">查看评论</a> ·\n<a href=\"http://www.weibo.com/ifanr\">新浪微博</a>\n</p>\n\n<br />\n<div style=\"text-align: center; border-top: 1px dotted #ccc;\">\n</div>", 
  "title": "ARM 发布两款全新 CPU 架构，骁龙 845 可能会用上"
 }, 
 {
  "date": "Mon, 29 May 2017 10:55:55 +0000", 
  "link": "http://www.ifanr.com/844929?utm_source=rss&utm_medium=rss&utm_campaign=", 
  "description": "除了运动，苹果还打算为 Apple Watch 扩展更多的使用场景。<p>#欢迎关注爱范儿官方微信公众号：爱范儿（微信号：ifanr），更多精彩内容第一时间为您奉上。</p><p>\n<a href=\"http://www.ifanr.com\">爱范儿</a> |\n<a href=\"http://www.ifanr.com/844929\">原文链接</a> ·\n<a href=\"http://www.ifanr.com/844929#comments\">查看评论</a> ·\n<a href=\"http://www.weibo.com/ifanr\">新浪微博</a>\n</p>\n\n<br />\n<div style=\"text-align: center; border-top: 1px dotted #ccc;\">\n</div>", 
  "title": "加上这些功能后，你会考虑买个 Apple Watch 吗？"
 }, 
 {
  "date": "Mon, 29 May 2017 08:25:18 +0000", 
  "link": "http://www.ifanr.com/844905?utm_source=rss&utm_medium=rss&utm_campaign=", 
  "description": "这是一场围绕泛娱乐场景的用户争夺战。<p>#欢迎关注爱范儿官方微信公众号：爱范儿（微信号：ifanr），更多精彩内容第一时间为您奉上。</p><p>\n<a href=\"http://www.ifanr.com\">爱范儿</a> |\n<a href=\"http://www.ifanr.com/844905\">原文链接</a> ·\n<a href=\"http://www.ifanr.com/844905#comments\">查看评论</a> ·\n<a href=\"http://www.weibo.com/ifanr\">新浪微博</a>\n</p>\n\n<br />\n<div style=\"text-align: center; border-top: 1px dotted #ccc;\">\n</div>", 
  "title": "陌陌、微博和快手，视频化三巨头终有一战"
 }, 
 {
  "date": "Mon, 29 May 2017 07:40:44 +0000", 
  "link": "http://www.ifanr.com/844852?utm_source=rss&utm_medium=rss&utm_campaign=", 
  "description": "然而你会轻易抛弃后两者吗？<p>#欢迎关注爱范儿官方微信公众号：爱范儿（微信号：ifanr），更多精彩内容第一时间为您奉上。</p><p>\n<a href=\"http://www.ifanr.com\">爱范儿</a> |\n<a href=\"http://www.ifanr.com/844852\">原文链接</a> ·\n<a href=\"http://www.ifanr.com/844852#comments\">查看评论</a> ·\n<a href=\"http://www.weibo.com/ifanr\">新浪微博</a>\n</p>\n\n<br />\n<div style=\"text-align: center; border-top: 1px dotted #ccc;\">\n</div>", 
  "title": "银联想赶上微信和支付宝，也要让大家来“扫一扫”"
 }, 
 {
  "date": "Mon, 29 May 2017 03:42:28 +0000", 
  "link": "http://www.ifanr.com/844837?utm_source=rss&utm_medium=rss&utm_campaign=", 
  "description": "英伟达将在今年 9 月 Project Holodeck 发布早期测试版。<p>#欢迎关注爱范儿官方微信公众号：爱范儿（微信号：ifanr），更多精彩内容第一时间为您奉上。</p><p>\n<a href=\"http://www.ifanr.com\">爱范儿</a> |\n<a href=\"http://www.ifanr.com/844837\">原文链接</a> ·\n<a href=\"http://www.ifanr.com/844837#comments\">查看评论</a> ·\n<a href=\"http://www.weibo.com/ifanr\">新浪微博</a>\n</p>\n\n<br />\n<div style=\"text-align: center; border-top: 1px dotted #ccc;\">\n</div>", 
  "title": "超前的英伟达，和他的《星际迷航》全息甲板梦"
 }, 
 {
  "date": "Sun, 28 May 2017 11:52:47 +0000", 
  "link": "http://www.ifanr.com/844710?utm_source=rss&utm_medium=rss&utm_campaign=", 
  "description": "用上 iPad 的“大触”越来越多。<p>#欢迎关注爱范儿官方微信公众号：爱范儿（微信号：ifanr），更多精彩内容第一时间为您奉上。</p><p>\n<a href=\"http://www.ifanr.com\">爱范儿</a> |\n<a href=\"http://www.ifanr.com/844710\">原文链接</a> ·\n<a href=\"http://www.ifanr.com/844710#comments\">查看评论</a> ·\n<a href=\"http://www.weibo.com/ifanr\">新浪微博</a>\n</p>\n\n<br />\n<div style=\"text-align: center; border-top: 1px dotted #ccc;\">\n</div>", 
  "title": "《纽约客》新封面 iPad 绘制，苹果生产力转型成效如何？"
 }, 
 {
  "date": "Sun, 28 May 2017 10:15:35 +0000", 
  "link": "http://www.ifanr.com/844675?utm_source=rss&utm_medium=rss&utm_campaign=", 
  "description": "内容才是国内 VR 发展的出口。<p>#欢迎关注爱范儿官方微信公众号：爱范儿（微信号：ifanr），更多精彩内容第一时间为您奉上。</p><p>\n<a href=\"http://www.ifanr.com\">爱范儿</a> |\n<a href=\"http://www.ifanr.com/844675\">原文链接</a> ·\n<a href=\"http://www.ifanr.com/844675#comments\">查看评论</a> ·\n<a href=\"http://www.weibo.com/ifanr\">新浪微博</a>\n</p>\n\n<br />\n<div style=\"text-align: center; border-top: 1px dotted #ccc;\">\n</div>", 
  "title": "5 月，国内 VR 内容喜讯不断，VR 内容真的要爆发了么？"
 }, 
 {
  "date": "Sun, 28 May 2017 09:35:48 +0000", 
  "link": "http://www.ifanr.com/844714?utm_source=rss&utm_medium=rss&utm_campaign=", 
  "description": "这是一篇考古挖坟文。<p>#欢迎关注爱范儿官方微信公众号：爱范儿（微信号：ifanr），更多精彩内容第一时间为您奉上。</p><p>\n<a href=\"http://www.ifanr.com\">爱范儿</a> |\n<a href=\"http://www.ifanr.com/844714\">原文链接</a> ·\n<a href=\"http://www.ifanr.com/844714#comments\">查看评论</a> ·\n<a href=\"http://www.weibo.com/ifanr\">新浪微博</a>\n</p>\n\n<br />\n<div style=\"text-align: center; border-top: 1px dotted #ccc;\">\n</div>", 
  "title": "猜猜看，哪代 iPhone 组装成本最低？"
 }, 
 {
  "date": "Sun, 28 May 2017 07:06:35 +0000", 
  "link": "http://www.ifanr.com/844648?utm_source=rss&utm_medium=rss&utm_campaign=", 
  "description": "回顾一周汽车行业重要新闻。<p>#欢迎关注爱范儿官方微信公众号：爱范儿（微信号：ifanr），更多精彩内容第一时间为您奉上。</p><p>\n<a href=\"http://www.ifanr.com\">爱范儿</a> |\n<a href=\"http://www.ifanr.com/844648\">原文链接</a> ·\n<a href=\"http://www.ifanr.com/844648#comments\">查看评论</a> ·\n<a href=\"http://www.weibo.com/ifanr\">新浪微博</a>\n</p>\n\n<br />\n<div style=\"text-align: center; border-top: 1px dotted #ccc;\">\n</div>", 
  "title": "法拉第未来欲融资 10 亿美元 上汽奥迪也要来了？ | 五分钟汽车周报"
 }, 
 {
  "date": "Sun, 28 May 2017 03:44:05 +0000", 
  "link": "http://www.ifanr.com/844563?utm_source=rss&utm_medium=rss&utm_campaign=", 
  "description": "英国航空的飞机们还没起飞就成了全世界的头条，因为它们飞不起来了。<p>#欢迎关注爱范儿官方微信公众号：爱范儿（微信号：ifanr），更多精彩内容第一时间为您奉上。</p><p>\n<a href=\"http://www.ifanr.com\">爱范儿</a> |\n<a href=\"http://www.ifanr.com/844563\">原文链接</a> ·\n<a href=\"http://www.ifanr.com/844563#comments\">查看评论</a> ·\n<a href=\"http://www.weibo.com/ifanr\">新浪微博</a>\n</p>\n\n<br />\n<div style=\"text-align: center; border-top: 1px dotted #ccc;\">\n</div>", 
  "title": "英国航空系统出错造成大面积航班取消，有人说元凶一年前就出现了"
 }, 
 {
  "date": "Sun, 28 May 2017 02:51:03 +0000", 
  "link": "http://www.ifanr.com/844542?utm_source=rss&utm_medium=rss&utm_campaign=", 
  "description": "LG 对双屏幕是真爱阿。<p>#欢迎关注爱范儿官方微信公众号：爱范儿（微信号：ifanr），更多精彩内容第一时间为您奉上。</p><p>\n<a href=\"http://www.ifanr.com\">爱范儿</a> |\n<a href=\"http://www.ifanr.com/844542\">原文链接</a> ·\n<a href=\"http://www.ifanr.com/844542#comments\">查看评论</a> ·\n<a href=\"http://www.weibo.com/ifanr\">新浪微博</a>\n</p>\n\n<br />\n<div style=\"text-align: center; border-top: 1px dotted #ccc;\">\n</div>", 
  "title": "滑盖双屏！这样的 LG V30 你会喜欢吗？"
 }, 
 {
  "date": "Sat, 27 May 2017 09:45:20 +0000", 
  "link": "http://www.ifanr.com/844439?utm_source=rss&utm_medium=rss&utm_campaign=", 
  "description": "欢迎进来表个态<p>#欢迎关注爱范儿官方微信公众号：爱范儿（微信号：ifanr），更多精彩内容第一时间为您奉上。</p><p>\n<a href=\"http://www.ifanr.com\">爱范儿</a> |\n<a href=\"http://www.ifanr.com/844439\">原文链接</a> ·\n<a href=\"http://www.ifanr.com/844439#comments\">查看评论</a> ·\n<a href=\"http://www.weibo.com/ifanr\">新浪微博</a>\n</p>\n\n<br />\n<div style=\"text-align: center; border-top: 1px dotted #ccc;\">\n</div>", 
  "title": "你说，要怎样你才愿意去吃“人造肉”？"
 }, 
 {
  "date": "Sat, 27 May 2017 08:49:14 +0000", 
  "link": "http://www.ifanr.com/844359?utm_source=rss&utm_medium=rss&utm_campaign=", 
  "description": "这次请来了超模 Bella 代言，不过周年庆的设计师大概是最轻松的。<p>#欢迎关注爱范儿官方微信公众号：爱范儿（微信号：ifanr），更多精彩内容第一时间为您奉上。</p><p>\n<a href=\"http://www.ifanr.com\">爱范儿</a> |\n<a href=\"http://www.ifanr.com/844359\">原文链接</a> ·\n<a href=\"http://www.ifanr.com/844359#comments\">查看评论</a> ·\n<a href=\"http://www.weibo.com/ifanr\">新浪微博</a>\n</p>\n\n<br />\n<div style=\"text-align: center; border-top: 1px dotted #ccc;\">\n</div>", 
  "title": "耐克“阿甘鞋”45 周年纪念，又是一款经典复刻"
 }, 
 {
  "date": "Sat, 27 May 2017 08:28:14 +0000", 
  "link": "http://www.ifanr.com/844318?utm_source=rss&utm_medium=rss&utm_campaign=", 
  "description": "不得不说，《怪物猎人》的影响力真是很可怕…<p>#欢迎关注爱范儿官方微信公众号：爱范儿（微信号：ifanr），更多精彩内容第一时间为您奉上。</p><p>\n<a href=\"http://www.ifanr.com\">爱范儿</a> |\n<a href=\"http://www.ifanr.com/844318\">原文链接</a> ·\n<a href=\"http://www.ifanr.com/844318#comments\">查看评论</a> ·\n<a href=\"http://www.weibo.com/ifanr\">新浪微博</a>\n</p>\n\n<br />\n<div style=\"text-align: center; border-top: 1px dotted #ccc;\">\n</div>", 
  "title": "NS 版《怪物猎人XX》突然袭来，任天堂的股价暴涨创 9 年来新高！"
 }, 
 {
  "date": "Sat, 27 May 2017 07:42:23 +0000", 
  "link": "http://www.ifanr.com/844261?utm_source=rss&utm_medium=rss&utm_campaign=", 
  "description": "我们向 AlphaGo 致敬，向柯洁致敬。<p>#欢迎关注爱范儿官方微信公众号：爱范儿（微信号：ifanr），更多精彩内容第一时间为您奉上。</p><p>\n<a href=\"http://www.ifanr.com\">爱范儿</a> |\n<a href=\"http://www.ifanr.com/844261\">原文链接</a> ·\n<a href=\"http://www.ifanr.com/844261#comments\">查看评论</a> ·\n<a href=\"http://www.weibo.com/ifanr\">新浪微博</a>\n</p>\n\n<br />\n<div style=\"text-align: center; border-top: 1px dotted #ccc;\">\n</div>", 
  "title": "柯洁别哭！“狗”并不会笑"
 }
]