[
 {
  "date": "Thu, 28 Nov 2013 02:59:06 +0000", 
  "link": "http://www.ifanr.com/380777?utm_source=rss&utm_medium=rss&utm_campaign=", 
  "description": "智能电视盒子是今年大热设备之一，对于已经进军手机行业的阿里巴巴来说，进军客厅也是迟早的事，但想不到阿里这次发的是一记狠招：只要在这个双十一当天在天猫超市消费满 88 元，就会免费向你派送一部旗下的智能电视盒——天猫魔盒。 这次爱范儿收到的这款天猫魔盒，是一款将智能电视、电视购物合于一体的电视盒产品，一起看看体验如何。 外观 首先说说天猫魔盒的外观，作为一款“准免费”产品（目前淘宝上价格为 250 上下），天猫魔盒的包装非常简单，但没有廉价感。整体使用白色整体+红色点缀，反倒带有日系小清新风格。包装在成本和设计作了出色的平衡，能给人一个不错的第一印象。 包装里的内容，如果用量来衡量的话，阵容算是不错。除了天猫魔盒本体外，包含一枚遥控器、一条 HDMI 线、一条 AV 线、还有一个外接电源。对于其比 Apple TV 大一圈的体积来说，没有采用内置电源的设计让人有点遗憾，希望下次努力。 盒子本体的设计则为产品加分不少。机身大胆采用了茄汁红，配合底部萌呆的天猫，除了很好地体现了品牌配色外，产品萌属性直线飙升。就算是以男性消费者角度来看，家里客厅多了一款外形俏皮的电视盒子，不会感到抗拒。 而盒子最重要的配件——遥控器，则继续发挥俏皮路线，底部的天猫乱入算是整体设计的点睛之笔。说回遥控器本身，和其他的大路产品则无太大分别。 不过需要指出遥控器一点不太合理的设计，就是最频繁用到的三个按钮，“主页” 、 “菜单” 和 “返回” ，如果上面的圆形按键作为遥控器中心的话，前两者被安置在最上方，但 “返回” 却安排在下方，拇指需要经常下来来回奔波，造成不必要的劳累感。看不出这样设计有什么好处，颇有画蛇添足的味道，或许只是为了避开小米盒子的设计？ 另外，附带的说明书也和包装一样，非常简洁，但设计和质量都非常不错。 从整体设计上看，天猫魔盒算是一款对得起观众的产品。接下来看看硬件部分。 &#160; 配置 大致罗烈一下产品的配置： CPU：Cortex-A9 双核 1.5GHz 内存：1 GB 储存空间：4GB 接口：USB、MicroSD（支持最大 32GB）、10/100 以太网、802.11 b/g/n WiFi、HDMI 1.4 系统：YunOS 1.2.0（基于 Android 开发） 配置上来看，除了最近流行的蓝牙 4.0 缺席之外，天猫魔盒算是主流。 而机身后的接口也比较丰富，从左至右分别是电源、全尺寸 USB、MicroSD、A/V、HDMI 以及以太网接口。和 Apple TV [&#8230;]<p>#欢迎关注爱范儿认证微信公众号：AppSolution（微信号：appsolution），发现新酷精华应用。</p><img border=\"0\" src=\"http://ifanr.feedsportal.com/c/33866/f/642084/s/380777/mf.gif\" /><br /><br /><a href=\"http://da.feedsportal.com/r/144540365956/u/362/f/642084/c/33866/s/380777/a2.htm\"><img border=\"0\" src=\"http://da.feedsportal.com/r/144540365956/u/362/f/642084/c/33866/s/380777/a2.img\" /></a><img border=\"0\" height=\"1\" src=\"http://pi.feedsportal.com/r/144540365956/u/362/f/642084/c/33866/s/380777/a2t.img\" width=\"1\" /><p>\n<a href=\"http://www.ifanr.com\">爱范儿 · Beats of Bits</a> |\n<a href=\"http://www.ifanr.com/380777\">原文链接</a> ·\n<a href=\"http://www.ifanr.com/380777#comments\">查看评论</a> ·\n<a href=\"http://www.weibo.com/ifanr\">新浪微博</a> ·\n<a href=\"http://www.ifanr.com/weixin\">微信订阅</a> ·\n<a href=\"http://bbs.ifanr.com/\">加入爱范社区！</a> \n</p>\n\n<br />\n<div style=\"text-align: center; border-top: 1px dotted #ccc;\">\n</div>", 
  "title": "一只智能电视界萌猫：天猫魔盒评测"
 }, 
 {
  "date": "Thu, 28 Nov 2013 02:57:26 +0000", 
  "link": "http://www.ifanr.com/news/380739?utm_source=rss&utm_medium=rss&utm_campaign=", 
  "description": "据 WPCentral 报道，AdDuplex 发布的最新数据显示，诺基亚占据了全球 WP 市场 90% 的份额，并且该公司旗下的低端机型 Lumia 520 是 WP 阵营中毫无争议的主力机型（数据截至 2013 年 11 月 22 日）。 全球 90% 的 WP 设备均出自诺基亚之手，HTC 以 7% 的市场份额位列第二，三星、华为的份额分别只有 1.8% 和 1.3%。考虑到微软即将买下诺基亚设备与服务部门（交易明年初完成）， 未来诺基亚在 WP 的统治地位可能会更加牢固。 全球 WP 手机各机型份额方面，榜上有名的全是诺基亚手机，HTC、三星、华为旗下设备已经被归为“其他”类别。低端机型 Lumia 520 在 WP 阵营中的份额高达 26.5%，是唯一一款份额达到两位数的手机。或许能让诺基亚舒心的是，高端机型 Lumia 920 份额已经达到了 8.8%，位居第二。 此外，Windows Phone 7.x 依然占据了全部 WP 系统 24.7% 的份额，主要原因在于仍有许多人使用 Lumia 800、Lumia 710 等无缘 WP8 的设备（见上图）。目前 [&#8230;]<p>#欢迎关注爱范儿认证微信公众号：AppSolution（微信号：appsolution），发现新酷精华应用。</p><img border=\"0\" src=\"http://ifanr.feedsportal.com/c/33866/f/642084/s/380739/mf.gif\" /><br /><br /><a href=\"http://da.feedsportal.com/r/144540365956/u/362/f/642084/c/33866/s/380739/a2.htm\"><img border=\"0\" src=\"http://da.feedsportal.com/r/144540365956/u/362/f/642084/c/33866/s/380739/a2.img\" /></a><img border=\"0\" height=\"1\" src=\"http://pi.feedsportal.com/r/144540365956/u/362/f/642084/c/33866/s/380739/a2t.img\" width=\"1\" /><p>\n<a href=\"http://www.ifanr.com\">爱范儿 · Beats of Bits</a> |\n<a href=\"http://www.ifanr.com/news/380739\">原文链接</a> ·\n<a href=\"http://www.ifanr.com/news/380739#comments\">查看评论</a> ·\n<a href=\"http://www.weibo.com/ifanr\">新浪微博</a> ·\n<a href=\"http://www.ifanr.com/weixin\">微信订阅</a> ·\n<a href=\"http://bbs.ifanr.com/\">加入爱范社区！</a> \n</p>\n\n<br />\n<div style=\"text-align: center; border-top: 1px dotted #ccc;\">\n</div>", 
  "title": "全球 9 成 WP 手机来自诺基亚，Lumia 520 最风光"
 }
]