[
 {
  "date": "Thu, 15 Oct 2015 05:42:42 +0000", 
  "link": "http://www.ifanr.com/572399?utm_source=rss&utm_medium=rss&utm_campaign=", 
  "description": "未来 20 到 30 年才能实现真正的非高速路的完全自动驾驶。<p>#欢迎关注爱范儿认证微信公众号：AppSolution（微信号：appsolution），发现新酷精华应用。</p><img border=\"0\" src=\"http://ifanr.feedsportal.com/c/33866/f/642084/s/572399/mf.gif\" /><br /><br /><a href=\"http://da.feedsportal.com/r/144540365956/u/362/f/642084/c/33866/s/572399/a2.htm\"><img border=\"0\" src=\"http://da.feedsportal.com/r/144540365956/u/362/f/642084/c/33866/s/572399/a2.img\" /></a><img border=\"0\" height=\"1\" src=\"http://pi.feedsportal.com/r/144540365956/u/362/f/642084/c/33866/s/572399/a2t.img\" width=\"1\" /><p>\n<a href=\"http://www.ifanr.com\">爱范儿</a> |\n<a href=\"http://www.ifanr.com/572399\">原文链接</a> ·\n<a href=\"http://www.ifanr.com/572399#comments\">查看评论</a> ·\n<a href=\"http://www.weibo.com/ifanr\">新浪微博</a> ·\n<a href=\"http://www.ifanr.com/weixin\">微信订阅</a>\n</p>\n\n<br />\n<div style=\"text-align: center; border-top: 1px dotted #ccc;\">\n</div>", 
  "title": "完全自动驾驶还远，奥迪工程师理解的自动驾驶是这样的"
 }, 
 {
  "date": "Thu, 15 Oct 2015 03:50:10 +0000", 
  "link": "http://www.ifanr.com/572385?utm_source=rss&utm_medium=rss&utm_campaign=", 
  "description": "人生已经如此的艰难。<p>#欢迎关注爱范儿认证微信公众号：AppSolution（微信号：appsolution），发现新酷精华应用。</p><img border=\"0\" src=\"http://ifanr.feedsportal.com/c/33866/f/642084/s/572385/mf.gif\" /><br /><br /><a href=\"http://da.feedsportal.com/r/144540365956/u/362/f/642084/c/33866/s/572385/a2.htm\"><img border=\"0\" src=\"http://da.feedsportal.com/r/144540365956/u/362/f/642084/c/33866/s/572385/a2.img\" /></a><img border=\"0\" height=\"1\" src=\"http://pi.feedsportal.com/r/144540365956/u/362/f/642084/c/33866/s/572385/a2t.img\" width=\"1\" /><p>\n<a href=\"http://www.ifanr.com\">爱范儿</a> |\n<a href=\"http://www.ifanr.com/572385\">原文链接</a> ·\n<a href=\"http://www.ifanr.com/572385#comments\">查看评论</a> ·\n<a href=\"http://www.weibo.com/ifanr\">新浪微博</a> ·\n<a href=\"http://www.ifanr.com/weixin\">微信订阅</a>\n</p>\n\n<br />\n<div style=\"text-align: center; border-top: 1px dotted #ccc;\">\n</div>", 
  "title": "照片都不能随意分享，以后，还能不能愉快地发朋友圈了？"
 }, 
 {
  "date": "Thu, 15 Oct 2015 03:18:00 +0000", 
  "link": "http://www.ifanr.com/572118?utm_source=rss&utm_medium=rss&utm_campaign=", 
  "description": "这个 AW 既包括 Android Wear，也包括 Apple Watch。<p>#欢迎关注爱范儿认证微信公众号：AppSolution（微信号：appsolution），发现新酷精华应用。</p><img border=\"0\" src=\"http://ifanr.feedsportal.com/c/33866/f/642084/s/572118/mf.gif\" /><br /><br /><a href=\"http://da.feedsportal.com/r/144540365956/u/362/f/642084/c/33866/s/572118/a2.htm\"><img border=\"0\" src=\"http://da.feedsportal.com/r/144540365956/u/362/f/642084/c/33866/s/572118/a2.img\" /></a><img border=\"0\" height=\"1\" src=\"http://pi.feedsportal.com/r/144540365956/u/362/f/642084/c/33866/s/572118/a2t.img\" width=\"1\" /><p>\n<a href=\"http://www.ifanr.com\">爱范儿</a> |\n<a href=\"http://www.ifanr.com/572118\">原文链接</a> ·\n<a href=\"http://www.ifanr.com/572118#comments\">查看评论</a> ·\n<a href=\"http://www.weibo.com/ifanr\">新浪微博</a> ·\n<a href=\"http://www.ifanr.com/weixin\">微信订阅</a>\n</p>\n\n<br />\n<div style=\"text-align: center; border-top: 1px dotted #ccc;\">\n</div>", 
  "title": "三星 Gear S2 上手：不喜欢 AW 们，这是好选择"
 }, 
 {
  "date": "Thu, 15 Oct 2015 03:16:50 +0000", 
  "link": "http://www.ifanr.com/572378?utm_source=rss&utm_medium=rss&utm_campaign=", 
  "description": "别让我带两大箱电池就行。<p>#欢迎关注爱范儿认证微信公众号：AppSolution（微信号：appsolution），发现新酷精华应用。</p><img border=\"0\" src=\"http://ifanr.feedsportal.com/c/33866/f/642084/s/572378/mf.gif\" /><br /><br /><a href=\"http://da.feedsportal.com/r/144540365956/u/362/f/642084/c/33866/s/572378/a2.htm\"><img border=\"0\" src=\"http://da.feedsportal.com/r/144540365956/u/362/f/642084/c/33866/s/572378/a2.img\" /></a><img border=\"0\" height=\"1\" src=\"http://pi.feedsportal.com/r/144540365956/u/362/f/642084/c/33866/s/572378/a2t.img\" width=\"1\" /><p>\n<a href=\"http://www.ifanr.com\">爱范儿</a> |\n<a href=\"http://www.ifanr.com/572378\">原文链接</a> ·\n<a href=\"http://www.ifanr.com/572378#comments\">查看评论</a> ·\n<a href=\"http://www.weibo.com/ifanr\">新浪微博</a> ·\n<a href=\"http://www.ifanr.com/weixin\">微信订阅</a>\n</p>\n\n<br />\n<div style=\"text-align: center; border-top: 1px dotted #ccc;\">\n</div>", 
  "title": "穿戴到眼球也就算了，Google 还想用光能供电和通信"
 }, 
 {
  "date": "Thu, 15 Oct 2015 03:07:41 +0000", 
  "link": "http://www.ifanr.com/572349?utm_source=rss&utm_medium=rss&utm_campaign=", 
  "description": "手机：PC 你卖不好，难道怪我？\n<p>#欢迎关注爱范儿认证微信公众号：AppSolution（微信号：appsolution），发现新酷精华应用。</p><img border=\"0\" src=\"http://ifanr.feedsportal.com/c/33866/f/642084/s/572349/mf.gif\" /><br /><br /><a href=\"http://da.feedsportal.com/r/144540365956/u/362/f/642084/c/33866/s/572349/a2.htm\"><img border=\"0\" src=\"http://da.feedsportal.com/r/144540365956/u/362/f/642084/c/33866/s/572349/a2.img\" /></a><img border=\"0\" height=\"1\" src=\"http://pi.feedsportal.com/r/144540365956/u/362/f/642084/c/33866/s/572349/a2t.img\" width=\"1\" /><p>\n<a href=\"http://www.ifanr.com\">爱范儿</a> |\n<a href=\"http://www.ifanr.com/572349\">原文链接</a> ·\n<a href=\"http://www.ifanr.com/572349#comments\">查看评论</a> ·\n<a href=\"http://www.weibo.com/ifanr\">新浪微博</a> ·\n<a href=\"http://www.ifanr.com/weixin\">微信订阅</a>\n</p>\n\n<br />\n<div style=\"text-align: center; border-top: 1px dotted #ccc;\">\n</div>", 
  "title": "PC 众品牌抱团密谋下一轮销售战，只因手机卖得太好？"
 }, 
 {
  "date": "Thu, 15 Oct 2015 02:23:31 +0000", 
  "link": "http://www.ifanr.com/572321?utm_source=rss&utm_medium=rss&utm_campaign=", 
  "description": "站着办公真的更健康吗？<p>#欢迎关注爱范儿认证微信公众号：AppSolution（微信号：appsolution），发现新酷精华应用。</p><img border=\"0\" src=\"http://ifanr.feedsportal.com/c/33866/f/642084/s/572321/mf.gif\" /><br /><br /><a href=\"http://da.feedsportal.com/r/144540365956/u/362/f/642084/c/33866/s/572321/a2.htm\"><img border=\"0\" src=\"http://da.feedsportal.com/r/144540365956/u/362/f/642084/c/33866/s/572321/a2.img\" /></a><img border=\"0\" height=\"1\" src=\"http://pi.feedsportal.com/r/144540365956/u/362/f/642084/c/33866/s/572321/a2t.img\" width=\"1\" /><p>\n<a href=\"http://www.ifanr.com\">爱范儿</a> |\n<a href=\"http://www.ifanr.com/572321\">原文链接</a> ·\n<a href=\"http://www.ifanr.com/572321#comments\">查看评论</a> ·\n<a href=\"http://www.weibo.com/ifanr\">新浪微博</a> ·\n<a href=\"http://www.ifanr.com/weixin\">微信订阅</a>\n</p>\n\n<br />\n<div style=\"text-align: center; border-top: 1px dotted #ccc;\">\n</div>", 
  "title": "“久坐无益要多站”这句话只说对了一半"
 }, 
 {
  "date": "Thu, 15 Oct 2015 01:08:40 +0000", 
  "link": "http://www.ifanr.com/572251?utm_source=rss&utm_medium=rss&utm_campaign=", 
  "description": "深度解密苹果是如何制作和测试 Macintosh 配件。<p>#欢迎关注爱范儿认证微信公众号：AppSolution（微信号：appsolution），发现新酷精华应用。</p><img border=\"0\" src=\"http://ifanr.feedsportal.com/c/33866/f/642084/s/572251/mf.gif\" /><br /><br /><a href=\"http://da.feedsportal.com/r/144540365956/u/362/f/642084/c/33866/s/572251/a2.htm\"><img border=\"0\" src=\"http://da.feedsportal.com/r/144540365956/u/362/f/642084/c/33866/s/572251/a2.img\" /></a><img border=\"0\" height=\"1\" src=\"http://pi.feedsportal.com/r/144540365956/u/362/f/642084/c/33866/s/572251/a2t.img\" width=\"1\" /><p>\n<a href=\"http://www.ifanr.com\">爱范儿</a> |\n<a href=\"http://www.ifanr.com/572251\">原文链接</a> ·\n<a href=\"http://www.ifanr.com/572251#comments\">查看评论</a> ·\n<a href=\"http://www.weibo.com/ifanr\">新浪微博</a> ·\n<a href=\"http://www.ifanr.com/weixin\">微信订阅</a>\n</p>\n\n<br />\n<div style=\"text-align: center; border-top: 1px dotted #ccc;\">\n</div>", 
  "title": "苹果最高机密的实验室里到底藏着什么？"
 }, 
 {
  "date": "Wed, 14 Oct 2015 23:37:05 +0000", 
  "link": "http://www.ifanr.com/572248?utm_source=rss&utm_medium=rss&utm_campaign=", 
  "description": "滴滴车站上线；铁塔公司收购三大运营商资产；快递一天 1 亿件；Uber 提供快递业务。<p>#欢迎关注爱范儿认证微信公众号：AppSolution（微信号：appsolution），发现新酷精华应用。</p><img border=\"0\" src=\"http://ifanr.feedsportal.com/c/33866/f/642084/s/572248/mf.gif\" /><br /><br /><a href=\"http://da.feedsportal.com/r/144540365956/u/362/f/642084/c/33866/s/572248/a2.htm\"><img border=\"0\" src=\"http://da.feedsportal.com/r/144540365956/u/362/f/642084/c/33866/s/572248/a2.img\" /></a><img border=\"0\" height=\"1\" src=\"http://pi.feedsportal.com/r/144540365956/u/362/f/642084/c/33866/s/572248/a2t.img\" width=\"1\" /><p>\n<a href=\"http://www.ifanr.com\">爱范儿</a> |\n<a href=\"http://www.ifanr.com/572248\">原文链接</a> ·\n<a href=\"http://www.ifanr.com/572248#comments\">查看评论</a> ·\n<a href=\"http://www.weibo.com/ifanr\">新浪微博</a> ·\n<a href=\"http://www.ifanr.com/weixin\">微信订阅</a>\n</p>\n\n<br />\n<div style=\"text-align: center; border-top: 1px dotted #ccc;\">\n</div>", 
  "title": "特斯拉提供自动驾驶功能了，然而并…… | 爱范早读"
 }, 
 {
  "date": "Wed, 14 Oct 2015 23:05:52 +0000", 
  "link": "http://www.ifanr.com/572219?utm_source=rss&utm_medium=rss&utm_campaign=", 
  "description": "索尼新黑卡 RX1 RII 最引人注目的两点：与旗舰单反 a7R II 相同的 4200 万像素全画幅传感器，搭载了可变低通滤镜。<p>#欢迎关注爱范儿认证微信公众号：AppSolution（微信号：appsolution），发现新酷精华应用。</p><img border=\"0\" src=\"http://ifanr.feedsportal.com/c/33866/f/642084/s/572219/mf.gif\" /><br /><br /><a href=\"http://da.feedsportal.com/r/144540365956/u/362/f/642084/c/33866/s/572219/a2.htm\"><img border=\"0\" src=\"http://da.feedsportal.com/r/144540365956/u/362/f/642084/c/33866/s/572219/a2.img\" /></a><img border=\"0\" height=\"1\" src=\"http://pi.feedsportal.com/r/144540365956/u/362/f/642084/c/33866/s/572219/a2t.img\" width=\"1\" /><p>\n<a href=\"http://www.ifanr.com\">爱范儿</a> |\n<a href=\"http://www.ifanr.com/572219\">原文链接</a> ·\n<a href=\"http://www.ifanr.com/572219#comments\">查看评论</a> ·\n<a href=\"http://www.weibo.com/ifanr\">新浪微博</a> ·\n<a href=\"http://www.ifanr.com/weixin\">微信订阅</a>\n</p>\n\n<br />\n<div style=\"text-align: center; border-top: 1px dotted #ccc;\">\n</div>", 
  "title": "手机摄影时代，索尼居然在这台小 DC 上用了 4200 万像素的全画幅传感器"
 }, 
 {
  "date": "Wed, 14 Oct 2015 13:02:15 +0000", 
  "link": "http://www.ifanr.com/572167?utm_source=rss&utm_medium=rss&utm_campaign=", 
  "description": "把人完全沉浸在一个虚拟空间当中，体会另外一个世界，这种体验叫虚拟现实（英文 Virtual Reality，简称 VR）。由于体验上的完全不同，它有潜力引发一场新的交互和内容制作革命。这一次 iSeed 主题专访系列采访了数家专注虚拟现实领域的初创公司。本文是该采访系列的第四篇。 2013 年，Oculus Rift 还没推出第二代开发者套装（Oculus DK2）的时候，我在深圳的制汇节（Maker Faire）上看到一个来自北京的团队 Depth-VR，已经在自己的工程样机上实现了“头部位置追踪”的特性——而这正是 Oculus DK2 对比第一代产品最大的改进之一。 于是，Depth-VR 在技术、产品方面的前瞻性，以及技术开发的执行力给我留下了深刻的印象。时隔 2 年，Depth-VR 在经历多次产品迭代，内部调整之后，团队从开发虚拟现实头显设备，转移到虚拟现实输入设备。 尽管团队有所转型，但创始人李今显得十分有自信。他对爱范儿说： 目前，在消费者能够接受的成本范围内做到具备头部跟踪、手部控制器跟踪技术方案的，并且可以拿出完整 Demo 的只有我们一家。 无限延伸空间的光学位置追踪系统 据了解，Depth-VR 已经在新产品上投入了一年的时间来研发。按照李今的话来说，是“专为虚拟现实设计的低成本的大范围光学位置跟踪系统”。简单来说，就是 Depth-VR 可以通过多个摄像头，来确定一定空间大小内人的动作以及位置，并把这些数据实时地反馈在虚拟现实的世界里，实现实时的互动。 Depth-VR 光学位置追踪系统的 Demo，通过画中画可以看到有只手正试图抓 Hello Kitty 李今说，“从理论上，按照我们的方法， 4 个摄像头可以同时捕捉 200 个标记，以一个人有 3 个标记（头与双手）来看，相当于可以同时捕捉 65 个人人的动作。”不过，为了实现数据的精准，目前 Depth-VR 的是按照同时捕捉 2–3 人动作这个方向来设计这套尚未命名的系统。 这套系统的优越性在于，它可以便利的扩大位置跟踪的范围，用 2 个摄像头对角放置可以覆盖 4m*4m 的房间——不过为了实现位置跟踪的精确性，一般团队现在会用 3 个摄像头。实际上，李今和团队曾经在在室外测试过上百平米空间内人的位置和动作的追踪。他说，“这不过是多增加几个摄像头而已，如果是数据传输方面，我们可以通过有线的方式来解决。” [&#8230;]<p>#欢迎关注爱范儿认证微信公众号：AppSolution（微信号：appsolution），发现新酷精华应用。</p><img border=\"0\" src=\"http://ifanr.feedsportal.com/c/33866/f/642084/s/572167/mf.gif\" /><br /><br /><a href=\"http://da.feedsportal.com/r/144540365956/u/362/f/642084/c/33866/s/572167/a2.htm\"><img border=\"0\" src=\"http://da.feedsportal.com/r/144540365956/u/362/f/642084/c/33866/s/572167/a2.img\" /></a><img border=\"0\" height=\"1\" src=\"http://pi.feedsportal.com/r/144540365956/u/362/f/642084/c/33866/s/572167/a2t.img\" width=\"1\" /><p>\n<a href=\"http://www.ifanr.com\">爱范儿</a> |\n<a href=\"http://www.ifanr.com/572167\">原文链接</a> ·\n<a href=\"http://www.ifanr.com/572167#comments\">查看评论</a> ·\n<a href=\"http://www.weibo.com/ifanr\">新浪微博</a> ·\n<a href=\"http://www.ifanr.com/weixin\">微信订阅</a>\n</p>\n\n<br />\n<div style=\"text-align: center; border-top: 1px dotted #ccc;\">\n</div>", 
  "title": "做了 2 年 VR 头盔，Depth-VR 为什么忍痛转型做交互？ | iSeed"
 }, 
 {
  "date": "Wed, 14 Oct 2015 11:34:44 +0000", 
  "link": "http://www.ifanr.com/572115?utm_source=rss&utm_medium=rss&utm_campaign=", 
  "description": "用乐高的思维玩手表，各有所思，各取所需。<p>#欢迎关注爱范儿认证微信公众号：AppSolution（微信号：appsolution），发现新酷精华应用。</p><img border=\"0\" src=\"http://ifanr.feedsportal.com/c/33866/f/642084/s/572115/mf.gif\" /><br /><br /><a href=\"http://da.feedsportal.com/r/144540365956/u/362/f/642084/c/33866/s/572115/a2.htm\"><img border=\"0\" src=\"http://da.feedsportal.com/r/144540365956/u/362/f/642084/c/33866/s/572115/a2.img\" /></a><img border=\"0\" height=\"1\" src=\"http://pi.feedsportal.com/r/144540365956/u/362/f/642084/c/33866/s/572115/a2t.img\" width=\"1\" /><p>\n<a href=\"http://www.ifanr.com\">爱范儿</a> |\n<a href=\"http://www.ifanr.com/572115\">原文链接</a> ·\n<a href=\"http://www.ifanr.com/572115#comments\">查看评论</a> ·\n<a href=\"http://www.weibo.com/ifanr\">新浪微博</a> ·\n<a href=\"http://www.ifanr.com/weixin\">微信订阅</a>\n</p>\n\n<br />\n<div style=\"text-align: center; border-top: 1px dotted #ccc;\">\n</div>", 
  "title": "别太迷恋陀飞轮，其实手表还能这么玩"
 }, 
 {
  "date": "Wed, 14 Oct 2015 11:02:21 +0000", 
  "link": "http://www.ifanr.com/572122?utm_source=rss&utm_medium=rss&utm_campaign=", 
  "description": "深入苹果，挖掘 iMac 背后的故事。预警：干货太多，文章很长。<p>#欢迎关注爱范儿认证微信公众号：AppSolution（微信号：appsolution），发现新酷精华应用。</p><img border=\"0\" src=\"http://ifanr.feedsportal.com/c/33866/f/642084/s/572122/mf.gif\" /><br /><br /><a href=\"http://da.feedsportal.com/r/144540365956/u/362/f/642084/c/33866/s/572122/a2.htm\"><img border=\"0\" src=\"http://da.feedsportal.com/r/144540365956/u/362/f/642084/c/33866/s/572122/a2.img\" /></a><img border=\"0\" height=\"1\" src=\"http://pi.feedsportal.com/r/144540365956/u/362/f/642084/c/33866/s/572122/a2t.img\" width=\"1\" /><p>\n<a href=\"http://www.ifanr.com\">爱范儿</a> |\n<a href=\"http://www.ifanr.com/572122\">原文链接</a> ·\n<a href=\"http://www.ifanr.com/572122#comments\">查看评论</a> ·\n<a href=\"http://www.weibo.com/ifanr\">新浪微博</a> ·\n<a href=\"http://www.ifanr.com/weixin\">微信订阅</a>\n</p>\n\n<br />\n<div style=\"text-align: center; border-top: 1px dotted #ccc;\">\n</div>", 
  "title": "深度内幕：新一代 iMac 背后的故事"
 }, 
 {
  "date": "Wed, 14 Oct 2015 10:24:13 +0000", 
  "link": "http://www.ifanr.com/571917?utm_source=rss&utm_medium=rss&utm_campaign=", 
  "description": "已经演唱会发布会分不清的我只能祈祷一下，白永祥的普通话不要再进步了，他语速再快些的话，我就跟不上魅族的节奏了。<p>#欢迎关注爱范儿认证微信公众号：AppSolution（微信号：appsolution），发现新酷精华应用。</p><img border=\"0\" src=\"http://ifanr.feedsportal.com/c/33866/f/642084/s/571917/mf.gif\" /><br /><br /><a href=\"http://da.feedsportal.com/r/144540365956/u/362/f/642084/c/33866/s/571917/a2.htm\"><img border=\"0\" src=\"http://da.feedsportal.com/r/144540365956/u/362/f/642084/c/33866/s/571917/a2.img\" /></a><img border=\"0\" height=\"1\" src=\"http://pi.feedsportal.com/r/144540365956/u/362/f/642084/c/33866/s/571917/a2t.img\" width=\"1\" /><p>\n<a href=\"http://www.ifanr.com\">爱范儿</a> |\n<a href=\"http://www.ifanr.com/571917\">原文链接</a> ·\n<a href=\"http://www.ifanr.com/571917#comments\">查看评论</a> ·\n<a href=\"http://www.weibo.com/ifanr\">新浪微博</a> ·\n<a href=\"http://www.ifanr.com/weixin\">微信订阅</a>\n</p>\n\n<br />\n<div style=\"text-align: center; border-top: 1px dotted #ccc;\">\n</div>", 
  "title": "魅族是如何从一年一度的发布会，变成现在一月一次的演唱会？"
 }, 
 {
  "date": "Wed, 14 Oct 2015 10:06:00 +0000", 
  "link": "http://www.ifanr.com/571782?utm_source=rss&utm_medium=rss&utm_campaign=", 
  "description": "相比 iPhone 6 竟然没进步？<p>#欢迎关注爱范儿认证微信公众号：AppSolution（微信号：appsolution），发现新酷精华应用。</p><img border=\"0\" src=\"http://ifanr.feedsportal.com/c/33866/f/642084/s/571782/mf.gif\" /><br /><br /><a href=\"http://da.feedsportal.com/r/144540365956/u/362/f/642084/c/33866/s/571782/a2.htm\"><img border=\"0\" src=\"http://da.feedsportal.com/r/144540365956/u/362/f/642084/c/33866/s/571782/a2.img\" /></a><img border=\"0\" height=\"1\" src=\"http://pi.feedsportal.com/r/144540365956/u/362/f/642084/c/33866/s/571782/a2t.img\" width=\"1\" /><p>\n<a href=\"http://www.ifanr.com\">爱范儿</a> |\n<a href=\"http://www.ifanr.com/571782\">原文链接</a> ·\n<a href=\"http://www.ifanr.com/571782#comments\">查看评论</a> ·\n<a href=\"http://www.weibo.com/ifanr\">新浪微博</a> ·\n<a href=\"http://www.ifanr.com/weixin\">微信订阅</a>\n</p>\n\n<br />\n<div style=\"text-align: center; border-top: 1px dotted #ccc;\">\n</div>", 
  "title": "iPhone 6s 拍照最好？DxO 并不这么认为"
 }, 
 {
  "date": "Wed, 14 Oct 2015 09:24:33 +0000", 
  "link": "http://www.ifanr.com/571775?utm_source=rss&utm_medium=rss&utm_campaign=", 
  "description": "马云的演讲还是那么有感染力。而这一次的云栖大会，按照官方给出的数据，两万多人规模，也算得上是云计算的一次盛会了<p>#欢迎关注爱范儿认证微信公众号：AppSolution（微信号：appsolution），发现新酷精华应用。</p><img border=\"0\" src=\"http://ifanr.feedsportal.com/c/33866/f/642084/s/571775/mf.gif\" /><br /><br /><a href=\"http://da.feedsportal.com/r/144540365956/u/362/f/642084/c/33866/s/571775/a2.htm\"><img border=\"0\" src=\"http://da.feedsportal.com/r/144540365956/u/362/f/642084/c/33866/s/571775/a2.img\" /></a><img border=\"0\" height=\"1\" src=\"http://pi.feedsportal.com/r/144540365956/u/362/f/642084/c/33866/s/571775/a2t.img\" width=\"1\" /><p>\n<a href=\"http://www.ifanr.com\">爱范儿</a> |\n<a href=\"http://www.ifanr.com/571775\">原文链接</a> ·\n<a href=\"http://www.ifanr.com/571775#comments\">查看评论</a> ·\n<a href=\"http://www.weibo.com/ifanr\">新浪微博</a> ·\n<a href=\"http://www.ifanr.com/weixin\">微信订阅</a>\n</p>\n\n<br />\n<div style=\"text-align: center; border-top: 1px dotted #ccc;\">\n</div>", 
  "title": "两万人的云栖大会，马云谈 DT 时代，不忘给创业者打鸡血"
 }
]