[
 {
  "date": "Tue, 21 Jan 2014 08:12:34 +0000", 
  "link": "http://www.ifanr.com/397109?utm_source=rss&utm_medium=rss&utm_campaign=", 
  "description": "本周四，诺基亚将发布 2013 财年第四季度的财报，而在诺基亚公布财报后不久，微软也将公布自己的季度财报。虽然双方的收购意向早已达成，诺基亚股东投票也通过了收购，但是要到今年第一季度，这项收购才会正式完成。 这份 2013 财年第四季度的财报也将会是诺基亚最后一份带有设备业务的财报，自此之后，诺基亚的三大业务将变为诺西通信（解决方案与网络业务 NSN）、HERE 地图和位置、先进技术。诺基亚在之前的财报预告中提到，诺基亚将在财报中将设备与服务部门归为“非持续性经营业务”。 纵有万般不舍，女儿终究还是要嫁人。在设备与服务部门划归到微软旗下之后，诺基亚的前路也并不平坦。 一直以来，诺基亚的设备部门和 HERE 地图部门都是处于亏损或保本的状态，所以诺西通信（解决方案与网络业务 NSN）成了诺基亚主要赚钱的部门，以弥补其他部门的损失。所以，诺基亚的经营状况很大程度上由诺西通信的业绩来决定的。 一个不好的消息是，随着诺西通信在韩国和日本的重大项目结束，诺西通信的盈利能力堪忧，预计该部门在第四季度的销售额同比下降 19%，为 32 亿欧元（约 43 亿美元），2013 财年全年的销售额也将下滑 17%，为 114 亿欧元（154 亿美元）。具体数额将在本周四晚 8 点财报中揭晓。 而在 2013 财年第三季度，诺西通信的销售额为 35.8 亿美元，同比下滑 26%，即使作为今后诺基亚的支柱业务，诺西通信在与爱立信和华为等厂商的竞争中还是处于不利位置。 诺西通信部门的主管 Rajeev Suri 曾表示，公司的当务之急是增加营收，而不是提高利润率。即使要做出这样的决断，诺基亚仍希望利润率最好维持在 8% 到 10% 之间。 不过第四季度的财报中，利润率可能还会维持在 12% 的高位，上下浮动 4%，第三季度诺西通信的利润率为 8%。而诺西通信的对手，爱立信和华为的利润率都比这要低。 在亚洲地区高速无线宽带网络业务量衰减之后，诺西通信面临的问题是找到一个新的业务来弥补这部分的损失，以 2013 年第三季度诺西通信 35.8 亿美元的营收为例，其中 41% 来自亚洲。 对行业而言的一个好消息是，全球电信运营商在 2014 年的网络设备开支有望增多，但是这个行业竞争依然激烈。 至于快要离开诺基亚的设备与服务部门，归咎于功能机退居二线的原因，诺基亚手机的整体出货量将会下降，但 Lumia 智能手机的出货量将较 2012 年同期大幅增长 [&#8230;]<p>#欢迎关注爱范儿认证微信公众号：AppSolution（微信号：appsolution），发现新酷精华应用。</p><img border=\"0\" src=\"http://ifanr.feedsportal.com/c/33866/f/642084/s/397109/mf.gif\" /><br /><br /><a href=\"http://da.feedsportal.com/r/144540365956/u/362/f/642084/c/33866/s/397109/a2.htm\"><img border=\"0\" src=\"http://da.feedsportal.com/r/144540365956/u/362/f/642084/c/33866/s/397109/a2.img\" /></a><img border=\"0\" height=\"1\" src=\"http://pi.feedsportal.com/r/144540365956/u/362/f/642084/c/33866/s/397109/a2t.img\" width=\"1\" /><p>\n<a href=\"http://www.ifanr.com\">爱范儿 · Beats of Bits</a> |\n<a href=\"http://www.ifanr.com/397109\">原文链接</a> ·\n<a href=\"http://www.ifanr.com/397109#comments\">查看评论</a> ·\n<a href=\"http://www.weibo.com/ifanr\">新浪微博</a> ·\n<a href=\"http://www.ifanr.com/weixin\">微信订阅</a> ·\n<a href=\"http://bbs.ifanr.com/\">加入爱范社区！</a> \n</p>\n\n<br />\n<div style=\"text-align: center; border-top: 1px dotted #ccc;\">\n</div>", 
  "title": "财报公布前瞻：没有手机，诺基亚前路依旧曲折"
 }, 
 {
  "date": "Tue, 21 Jan 2014 08:20:23 +0000", 
  "link": "http://www.ifanr.com/397171?utm_source=rss&utm_medium=rss&utm_campaign=", 
  "description": "小巧的 Mac mini 和炫酷的新款 Mac Pro 无疑突破了人们对计算机外形的想象。PC 主机还能设计成什么样？ Zotac 告诉你，球样。 Zotac 就推出了这样一款球形的 PC——ZBOX 01520。乍一看，ZBOX 01520 是一个黑色球体，颇类似 Nexus Q，不过，为了站立摆放和安置各种插槽，球形的两面采用立方的设计。 比如所有插槽都设置在设备背面，包括 4 个 USB 3.0 接口、3 个 USB 2.0 接口、HDMI、DisplayPort、耳机、Mic 插口和一个 SD 卡插口。 用户可以打开半个球体外壳看到 ZBOX 01520 的内部配置，不过作为一款 2014 年上市的 PC，ZBOX 01520 的配置着实不怎么样。ZBOX 01520 搭载了令人咋舌的英特尔酷睿 i3 4010U 处理器，集成 HD Graphics 4400 IGP 显卡，4GB 内存以及 500GB 硬盘。网络方面，ZBOX 01520 支持 [&#8230;]<p>#欢迎关注爱范儿认证微信公众号：AppSolution（微信号：appsolution），发现新酷精华应用。</p><img border=\"0\" src=\"http://ifanr.feedsportal.com/c/33866/f/642084/s/397171/mf.gif\" /><br /><br /><a href=\"http://da.feedsportal.com/r/144540365956/u/362/f/642084/c/33866/s/397171/a2.htm\"><img border=\"0\" src=\"http://da.feedsportal.com/r/144540365956/u/362/f/642084/c/33866/s/397171/a2.img\" /></a><img border=\"0\" height=\"1\" src=\"http://pi.feedsportal.com/r/144540365956/u/362/f/642084/c/33866/s/397171/a2t.img\" width=\"1\" /><p>\n<a href=\"http://www.ifanr.com\">爱范儿 · Beats of Bits</a> |\n<a href=\"http://www.ifanr.com/397171\">原文链接</a> ·\n<a href=\"http://www.ifanr.com/397171#comments\">查看评论</a> ·\n<a href=\"http://www.weibo.com/ifanr\">新浪微博</a> ·\n<a href=\"http://www.ifanr.com/weixin\">微信订阅</a> ·\n<a href=\"http://bbs.ifanr.com/\">加入爱范社区！</a> \n</p>\n\n<br />\n<div style=\"text-align: center; border-top: 1px dotted #ccc;\">\n</div>", 
  "title": "ZBOX 是个球？是台 PC"
 }
]