[
 {
  "date": "Tue, 05 May 2015 02:28:46 +0000", 
  "link": "http://www.ifanr.com/518009?utm_source=rss&utm_medium=rss&utm_campaign=", 
  "description": "据 Arstechnica 报道，新加坡总理李显龙日前在一次记者会上提到自己多年前写的一个程序，引起许多媒体和民众的好奇，于是总理在 Facebook 上 公布了该程序的 Google Drive 链接，并邀请大家来找 bug。 李显龙本科毕业于英国剑桥大学，获得数学和电脑科学双学士学位。由于有这个专业背景，不但写个程序不成问题，他还将对 IT 的热爱以及对科技前景的重视体现在了政治生涯中。去年年底在智慧国启动仪式上，他提出大力发展新加坡的科技建设，尤其是 IT 方面。李显龙的两个子女也继承了他对 IT 的热爱，双双毕业于 MIT，可谓真 IT 世家。 “程序语言课本总有天会成为我的退休读物” 2013 年时奥巴马曾录制视频呼吁全民写代码，硅谷科技大拿们对代码技术的推崇就更不必说，在我们生活已经被代码围绕的时候，似乎可以说“学点代码，很有必要”了。别人家总理都晒代码了，我们是否能期待编程成为今后的大学基础课，甚至进入义务教育和高考？ &#160; 题图：therealsingapore 插图：Arstechnica<p>#欢迎关注爱范儿认证微信公众号：AppSolution（微信号：appsolution），发现新酷精华应用。</p><img border=\"0\" src=\"http://ifanr.feedsportal.com/c/33866/f/642084/s/518009/mf.gif\" /><br /><br /><a href=\"http://da.feedsportal.com/r/144540365956/u/362/f/642084/c/33866/s/518009/a2.htm\"><img border=\"0\" src=\"http://da.feedsportal.com/r/144540365956/u/362/f/642084/c/33866/s/518009/a2.img\" /></a><img border=\"0\" height=\"1\" src=\"http://pi.feedsportal.com/r/144540365956/u/362/f/642084/c/33866/s/518009/a2t.img\" width=\"1\" /><a href=\"http://t.cn/RAnuUnx\">\n                    <img src=\"http://www.ifanr.com/wp-content/uploads/2015/04/zz1.jpg\" />\n                </a><p>\n<a href=\"http://www.ifanr.com\">爱范儿 · Beats of Bits</a> |\n<a href=\"http://www.ifanr.com/518009\">原文链接</a> ·\n<a href=\"http://www.ifanr.com/518009#comments\">查看评论</a> ·\n<a href=\"http://www.weibo.com/ifanr\">新浪微博</a> ·\n<a href=\"http://www.ifanr.com/weixin\">微信订阅</a>\n</p>\n\n<br />\n<div style=\"text-align: center; border-top: 1px dotted #ccc;\">\n</div>", 
  "title": "别人家的总理竟然是程序猿"
 }, 
 {
  "date": "Tue, 05 May 2015 02:26:35 +0000", 
  "link": "http://www.ifanr.com/518012?utm_source=rss&utm_medium=rss&utm_campaign=", 
  "description": "特斯拉 CEO Elon Musk 接受《日本经济新闻》采访时，谈及了 2013 年时 Elon Musk 曾考虑将特斯拉卖给 Google 的报道。 彭博社记者 Ashlee Vance 在即将出版的书中透露，2013 年时由于特斯拉经营状况不佳，Musk 希望 Google 能以 110 亿美元的溢价收购当时市值 60 亿美元的 Tesla，还希望 Google 让他能运营 Tesla 8 年时间或直到第 3 代产品面世，并且保证 Tesla 推出面向主流汽车市场的第 3 代产品前不要将公司分拆或关闭。 Elon Musk 表示： 我觉得彭博社夸大了当时的情况。我的确是跟 Google 方面有非正式的谈话，但是从未涉及到出资收购特斯拉。报道称 Google 要出自 60 亿美元来收购特斯拉，其实并没有那回事。 另外，在谈及了特斯拉在全球和日本市场销量问题的时候，Elon Musk 还用了不同寻常的谦逊态度，他表示： 我们并没有很大的野心。市场并不像我们预计那样。如果你看上一年的销售量就能知道，上一年全球市场我们卖出了 3.2 万辆。而今年的销量或许会略超 5 万辆，所以特斯拉在日本市场可能只有几千辆的销量，这并不是个很庞大的数字。 Elon [&#8230;]<p>#欢迎关注爱范儿认证微信公众号：AppSolution（微信号：appsolution），发现新酷精华应用。</p><img border=\"0\" src=\"http://ifanr.feedsportal.com/c/33866/f/642084/s/518012/mf.gif\" /><br /><br /><a href=\"http://da.feedsportal.com/r/144540365956/u/362/f/642084/c/33866/s/518012/a2.htm\"><img border=\"0\" src=\"http://da.feedsportal.com/r/144540365956/u/362/f/642084/c/33866/s/518012/a2.img\" /></a><img border=\"0\" height=\"1\" src=\"http://pi.feedsportal.com/r/144540365956/u/362/f/642084/c/33866/s/518012/a2t.img\" width=\"1\" /><a href=\"http://t.cn/RAnuUnx\">\n                    <img src=\"http://www.ifanr.com/wp-content/uploads/2015/04/zz1.jpg\" />\n                </a><p>\n<a href=\"http://www.ifanr.com\">爱范儿 · Beats of Bits</a> |\n<a href=\"http://www.ifanr.com/518012\">原文链接</a> ·\n<a href=\"http://www.ifanr.com/518012#comments\">查看评论</a> ·\n<a href=\"http://www.weibo.com/ifanr\">新浪微博</a> ·\n<a href=\"http://www.ifanr.com/weixin\">微信订阅</a>\n</p>\n\n<br />\n<div style=\"text-align: center; border-top: 1px dotted #ccc;\">\n</div>", 
  "title": "Elon Musk ：特斯拉才没想卖给 Google 呢！"
 }
]