[
 {
  "date": "Tue, 15 Nov 2016 03:04:59 +0000", 
  "link": "http://www.ifanr.com/747051?utm_source=rss&utm_medium=rss&utm_campaign=", 
  "description": "库克对 AR 的兴趣由来已久，而苹果进军 AR 领域，可能会从可穿戴设备——眼镜入手。<p>#欢迎关注爱范儿认证微信公众号：AppSolution（微信号：appsolution），发现新酷精华应用。</p><p>\n<a href=\"http://www.ifanr.com\">爱范儿</a> |\n<a href=\"http://www.ifanr.com/747051\">原文链接</a> ·\n<a href=\"http://www.ifanr.com/747051#comments\">查看评论</a> ·\n<a href=\"http://www.weibo.com/ifanr\">新浪微博</a>\n</p>\n\n<br />\n<div style=\"text-align: center; border-top: 1px dotted #ccc;\">\n</div>", 
  "title": "苹果可能要做眼镜了，而且还是 AR 眼镜"
 }, 
 {
  "date": "Tue, 15 Nov 2016 03:04:59 +0000", 
  "link": "http://www.ifanr.com/747049?utm_source=rss&utm_medium=rss&utm_campaign=", 
  "description": "还准备为了发长微博充会员吗？以后这笔钱可以省下来了。据腾讯科技 11 月 14 日消息，新浪微博近日悄悄取消了发布器的 140 字限制。据称此次开放限制后，包括普通用户在内的所有用户军可以可以发布多达 2000 字的长微博。<p>#欢迎关注爱范儿认证微信公众号：AppSolution（微信号：appsolution），发现新酷精华应用。</p><p>\n<a href=\"http://www.ifanr.com\">爱范儿</a> |\n<a href=\"http://www.ifanr.com/747049\">原文链接</a> ·\n<a href=\"http://www.ifanr.com/747049#comments\">查看评论</a> ·\n<a href=\"http://www.weibo.com/ifanr\">新浪微博</a>\n</p>\n\n<br />\n<div style=\"text-align: center; border-top: 1px dotted #ccc;\">\n</div>", 
  "title": "微博不“微”，放开 140 字限制是好事吗？"
 }, 
 {
  "date": "Tue, 15 Nov 2016 03:04:59 +0000", 
  "link": "http://www.ifanr.com/747047?utm_source=rss&utm_medium=rss&utm_campaign=", 
  "description": "今年的智能手机市场看起来没啥爆点，实则专利领域并不太平。<p>#欢迎关注爱范儿认证微信公众号：AppSolution（微信号：appsolution），发现新酷精华应用。</p><p>\n<a href=\"http://www.ifanr.com\">爱范儿</a> |\n<a href=\"http://www.ifanr.com/747047\">原文链接</a> ·\n<a href=\"http://www.ifanr.com/747047#comments\">查看评论</a> ·\n<a href=\"http://www.weibo.com/ifanr\">新浪微博</a>\n</p>\n\n<br />\n<div style=\"text-align: center; border-top: 1px dotted #ccc;\">\n</div>", 
  "title": "专利战烽烟再起，被告的也不止国产厂家"
 }
]