[
 {
  "date": "Thu, 08 Oct 2015 04:59:23 +0000", 
  "link": "http://www.ifanr.com/569281?utm_source=rss&utm_medium=rss&utm_campaign=", 
  "description": "今天是个好日子，大众点评和美团要和黄晓明杨颖抢新闻。<p>#欢迎关注爱范儿认证微信公众号：AppSolution（微信号：appsolution），发现新酷精华应用。</p><img border=\"0\" src=\"http://ifanr.feedsportal.com/c/33866/f/642084/s/569281/mf.gif\" /><br /><br /><a href=\"http://da.feedsportal.com/r/144540365956/u/362/f/642084/c/33866/s/569281/a2.htm\"><img border=\"0\" src=\"http://da.feedsportal.com/r/144540365956/u/362/f/642084/c/33866/s/569281/a2.img\" /></a><img border=\"0\" height=\"1\" src=\"http://pi.feedsportal.com/r/144540365956/u/362/f/642084/c/33866/s/569281/a2t.img\" width=\"1\" /><a href=\"http://mindstore.io/mind/5735/\">\n                    <img src=\"http://www.ifanr.com/wp-content/uploads/2015/09/rss-1.jpg\" />\n                </a><p>\n<a href=\"http://www.ifanr.com\">爱范儿</a> |\n<a href=\"http://www.ifanr.com/569281\">原文链接</a> ·\n<a href=\"http://www.ifanr.com/569281#comments\">查看评论</a> ·\n<a href=\"http://www.weibo.com/ifanr\">新浪微博</a> ·\n<a href=\"http://www.ifanr.com/weixin\">微信订阅</a>\n</p>\n\n<br />\n<div style=\"text-align: center; border-top: 1px dotted #ccc;\">\n</div>", 
  "title": "不再是传闻，大众点评和美团正式宣布合并"
 }, 
 {
  "date": "Thu, 08 Oct 2015 04:53:47 +0000", 
  "link": "http://www.ifanr.com/569146?utm_source=rss&utm_medium=rss&utm_campaign=", 
  "description": "广告太过猖狂，莫博士都看不下去了<p>#欢迎关注爱范儿认证微信公众号：AppSolution（微信号：appsolution），发现新酷精华应用。</p><img border=\"0\" src=\"http://ifanr.feedsportal.com/c/33866/f/642084/s/569146/mf.gif\" /><br /><br /><a href=\"http://da.feedsportal.com/r/144540365956/u/362/f/642084/c/33866/s/569146/a2.htm\"><img border=\"0\" src=\"http://da.feedsportal.com/r/144540365956/u/362/f/642084/c/33866/s/569146/a2.img\" /></a><img border=\"0\" height=\"1\" src=\"http://pi.feedsportal.com/r/144540365956/u/362/f/642084/c/33866/s/569146/a2t.img\" width=\"1\" /><a href=\"http://mindstore.io/mind/5735/\">\n                    <img src=\"http://www.ifanr.com/wp-content/uploads/2015/09/rss-1.jpg\" />\n                </a><p>\n<a href=\"http://www.ifanr.com\">爱范儿</a> |\n<a href=\"http://www.ifanr.com/569146\">原文链接</a> ·\n<a href=\"http://www.ifanr.com/569146#comments\">查看评论</a> ·\n<a href=\"http://www.weibo.com/ifanr\">新浪微博</a> ·\n<a href=\"http://www.ifanr.com/weixin\">微信订阅</a>\n</p>\n\n<br />\n<div style=\"text-align: center; border-top: 1px dotted #ccc;\">\n</div>", 
  "title": "莫森伯格：广告需要一场彻底的变革"
 }
]