[
 {
  "date": "Tue, 25 Dec 2018 11:49:20 +0000", 
  "link": "https://www.ifanr.com/1152544?utm_source=rss&utm_medium=rss&utm_campaign=", 
  "description": "定价太自信。<p>#欢迎关注爱范儿官方微信公众号：爱范儿（微信号：ifanr），更多精彩内容第一时间为您奉上。</p><p>\n<a href=\"https://www.ifanr.com\">爱范儿</a> |\n<a href=\"https://www.ifanr.com/1152544\">原文链接</a> ·\n<a href=\"https://www.ifanr.com/1152544#comments\">查看评论</a> ·\n<a href=\"https://weibo.com/ifanr\">新浪微博</a>\n</p>\n\n<br />\n<div style=\"text-align: center; border-top: 1px dotted #ccc;\">\n</div>", 
  "title": "卖得贵配置还低，本田的电摩凭啥干掉小牛"
 }, 
 {
  "date": "Tue, 25 Dec 2018 11:30:56 +0000", 
  "link": "https://www.ifanr.com/1152540?utm_source=rss&utm_medium=rss&utm_campaign=", 
  "description": "云存储是一门怎么样的生意？<p>#欢迎关注爱范儿官方微信公众号：爱范儿（微信号：ifanr），更多精彩内容第一时间为您奉上。</p><p>\n<a href=\"https://www.ifanr.com\">爱范儿</a> |\n<a href=\"https://www.ifanr.com/1152540\">原文链接</a> ·\n<a href=\"https://www.ifanr.com/1152540#comments\">查看评论</a> ·\n<a href=\"https://weibo.com/ifanr\">新浪微博</a>\n</p>\n\n<br />\n<div style=\"text-align: center; border-top: 1px dotted #ccc;\">\n</div>", 
  "title": "百度网盘要缩水了，这些年你用过多少家网盘？"
 }, 
 {
  "date": "Tue, 25 Dec 2018 11:06:08 +0000", 
  "link": "https://www.ifanr.com/1151584?utm_source=rss&utm_medium=rss&utm_campaign=", 
  "description": "别再说输在了起跑线，现在的孩子让你输在了娘胎里。<p>#欢迎关注爱范儿官方微信公众号：爱范儿（微信号：ifanr），更多精彩内容第一时间为您奉上。</p><p>\n<a href=\"https://www.ifanr.com\">爱范儿</a> |\n<a href=\"https://www.ifanr.com/1151584\">原文链接</a> ·\n<a href=\"https://www.ifanr.com/1151584#comments\">查看评论</a> ·\n<a href=\"https://weibo.com/ifanr\">新浪微博</a>\n</p>\n\n<br />\n<div style=\"text-align: center; border-top: 1px dotted #ccc;\">\n</div>", 
  "title": "一张照片卖到 17 万，这对 2 岁小孩是怎么做到的"
 }
]