[
 {
  "date": "Sun, 09 Aug 2015 03:40:09 +0000", 
  "link": "http://www.ifanr.com/550158?utm_source=rss&utm_medium=rss&utm_campaign=", 
  "description": "Design by Apple in California Assembled in China，使用过苹果设备的不会对这句话有陌生感。在苹果产业链中，苹果本身不直接制造和组装旗下产品，而是交由代工厂去做，承担着最终组装任务的，就包括台湾大厂富士康。很大程度上讲，富士康和苹果是相互成就的关系，背后则是中国巨大的人口红利。 这也无怪乎 Tim Cook 要在 Twitter 上赞扬富士康的中国女工。但是很明显的趋势是，国内人力成本这几年有了非常快的增长，富士康依托国内人口红利的道路也越来越不好走，作为人力密集型产业的代表，富士康必须找到未来的道路，发展机器人是措施之一，但这毕竟是远期战略。近期的话，可能把产业重心逐步迁往人力成本更低廉的地方。 在本周六，富士康和印度马哈拉施特拉邦（ Maharashtra）签署一项协议，在未来五年内投资 50 亿美元在此建造一座电子产品生产基地。签署协议的代表任务则是双方的最高级别任务，富士康创始人郭台铭以及哈拉施特拉邦的首席部长 Devendra Fadnavis。 当然，我们最大的疑问就是“Design by Apple in California Assembled in China”这句话会不会改成“Design by Apple in California Assembled in India”？按照常理，郭台铭对此则是不置可否，拒绝表态。 并且郭台铭还表示，富士康的一些合作伙伴，比如黑莓，小米和亚马逊也在寻找在印度的合作伙伴。 事实上，我们也可以这样认为，小米的成功因素中，供应链，目标市场和渠道的高度统一是一大功臣，这意味着中间的流通成本降低许多，中国是一个巨大的元器件供应地，生产组装地和全球最大的智能手机市场。不过明显的趋势是，中国工人的工资越来越高，智能手机市场也趋近饱和。而印度则被广泛认为是智能手机下一个高速增长的市场，在此建厂也可以认作是前瞻之举，不仅享受低人力成本的红利，也即将享受市场扩张的红利。 投资 50 亿美元在哈拉施特拉邦不是富士康的终点，郭台铭在这次印度之行中就走访印度多个邦省，寻找合适的合作可能。在此之前，郭台铭还表示，他们计划在 2020 年前在印度发展 10 到 12 个产业，不仅仅是工厂，还会有数据中心。 对此，印度方面肯定也表示欢迎，富士康的投资一则可以带动经济发展，拉动就业，据称，首先在马哈拉施特拉邦建造的工厂可以制造 50000 个就业机会。二则可以借由富士康巨大的产业号召力，带动其他厂商前来投资。 与之相对的是，富士康的主要产业还是留在中国，在生产高峰的时候，富士康的员工可以达到 130 万人，这已经可以匹敌一个国内的中型城市了，在如此巨大的员工数背后，是外界对于富士康员工的关注，其生产环境、员工生活成为媒体竞相报道的焦点，近几年的多起员工自杀事件则将富士康推向了舆论的风口浪尖。 &#160; 题图来自：vidaytiemposdeljuezroybean &#160;<p>#欢迎关注爱范儿认证微信公众号：AppSolution（微信号：appsolution），发现新酷精华应用。</p><img border=\"0\" src=\"http://ifanr.feedsportal.com/c/33866/f/642084/s/550158/mf.gif\" /><br /><br /><a href=\"http://da.feedsportal.com/r/144540365956/u/362/f/642084/c/33866/s/550158/a2.htm\"><img border=\"0\" src=\"http://da.feedsportal.com/r/144540365956/u/362/f/642084/c/33866/s/550158/a2.img\" /></a><img border=\"0\" height=\"1\" src=\"http://pi.feedsportal.com/r/144540365956/u/362/f/642084/c/33866/s/550158/a2t.img\" width=\"1\" /><a href=\"http://mindstore.io/mind/5279/\">\n                    <img src=\"http://www.ifanr.com/wp-content/uploads/2015/08/banner.jpg\" />\n                </a><p>\n<a href=\"http://www.ifanr.com\">爱范儿 · Beats of Bits</a> |\n<a href=\"http://www.ifanr.com/550158\">原文链接</a> ·\n<a href=\"http://www.ifanr.com/550158#comments\">查看评论</a> ·\n<a href=\"http://www.weibo.com/ifanr\">新浪微博</a> ·\n<a href=\"http://www.ifanr.com/weixin\">微信订阅</a>\n</p>\n\n<br />\n<div style=\"text-align: center; border-top: 1px dotted #ccc;\">\n</div>", 
  "title": "中国人力太贵，富士康把目光投向另一亚洲国家"
 }, 
 {
  "date": "Sun, 09 Aug 2015 03:37:41 +0000", 
  "link": "http://www.ifanr.com/550161?utm_source=rss&utm_medium=rss&utm_campaign=", 
  "description": "目前，3D 打印在诸多领域获得了广泛的应用。它可以打造个性化的玩具，也用于打印人体器官，还被用来制作动画片的人物和场景。最近，Singularityhub 采访了业界人士，探讨了 3D 打印在教育方面的潜力。 弗罗里达大学的 FCR-STEMLearn 项目使用了 3D 打印技术。研究人员与本地教师们合作，制造教育工具，确定课堂计划。“去年，我们向 250 位教师介绍了这个项目，如今，佛罗里达公立学校中，2 至 4 万名学生参与其中，” 研究员 Adam Santone 说，“毫无疑问，人们对 3D 打印有兴趣，同时，这有着把教师们变成本地教具供应工厂的潜力。” 教师、教育专家、科技界人士都认为，3D 打印可以让教师们快速制作更合适的教具，节省学校的预算，甚至有可能颠覆教育行业。更重要的是，它能够帮助人们创造更好的学习环境。不过，3D 打印要真正走进课堂，还要许多问题需要解决。 首先是，如何说服学校购买 3D 打印机，毕竟，这仍然是比较昂贵的技术。对此，FCR-STEMLearn 研究员 Rabien Razzouk 认为，从长期来看，3D 打印可以节省学校的预算。“在某些情况下，3D 打印教具比购买更为便宜。 以 DNA 模型来说，它们的费用大概是 250 美元，而且，一套教具用于 2 至 3 名学生。3D 打印可以节省费用，还可以打印任何缺失的部分。” 他说。 除了费用问题之外，要使 3D 打印充分发挥潜力，人们还要解决两个主要问题。一是，教师们的技能，二是 3D 打印周边的生态系统。“3D 打印仍然需要一定的技术。拥有必要技能的教师仍然是太少了。” 非盈利机构 NatureBytes 的设计师 Jon Fidler [&#8230;]<p>#欢迎关注爱范儿认证微信公众号：AppSolution（微信号：appsolution），发现新酷精华应用。</p><img border=\"0\" src=\"http://ifanr.feedsportal.com/c/33866/f/642084/s/550161/mf.gif\" /><br /><br /><a href=\"http://da.feedsportal.com/r/144540365956/u/362/f/642084/c/33866/s/550161/a2.htm\"><img border=\"0\" src=\"http://da.feedsportal.com/r/144540365956/u/362/f/642084/c/33866/s/550161/a2.img\" /></a><img border=\"0\" height=\"1\" src=\"http://pi.feedsportal.com/r/144540365956/u/362/f/642084/c/33866/s/550161/a2t.img\" width=\"1\" /><a href=\"http://mindstore.io/mind/5279/\">\n                    <img src=\"http://www.ifanr.com/wp-content/uploads/2015/08/banner.jpg\" />\n                </a><p>\n<a href=\"http://www.ifanr.com\">爱范儿 · Beats of Bits</a> |\n<a href=\"http://www.ifanr.com/550161\">原文链接</a> ·\n<a href=\"http://www.ifanr.com/550161#comments\">查看评论</a> ·\n<a href=\"http://www.weibo.com/ifanr\">新浪微博</a> ·\n<a href=\"http://www.ifanr.com/weixin\">微信订阅</a>\n</p>\n\n<br />\n<div style=\"text-align: center; border-top: 1px dotted #ccc;\">\n</div>", 
  "title": "3D 打印与教育：距离“按个按钮就打印”还很远"
 }
]