[
 {
  "date": "Sat, 17 Jun 2017 14:30:07 +0000", 
  "link": "http://www.ifanr.com/855762?utm_source=rss&utm_medium=rss&utm_campaign=", 
  "description": "原因有可能是因为忙。<p>#欢迎关注爱范儿官方微信公众号：爱范儿（微信号：ifanr），更多精彩内容第一时间为您奉上。</p><p>\n<a href=\"http://www.ifanr.com\">爱范儿</a> |\n<a href=\"http://www.ifanr.com/855762\">原文链接</a> ·\n<a href=\"http://www.ifanr.com/855762#comments\">查看评论</a> ·\n<a href=\"http://www.weibo.com/ifanr\">新浪微博</a>\n</p>\n\n<br />\n<div style=\"text-align: center; border-top: 1px dotted #ccc;\">\n</div>", 
  "title": "谁才是洋快餐真爱？美国中产！"
 }, 
 {
  "date": "Sat, 17 Jun 2017 12:46:22 +0000", 
  "link": "http://www.ifanr.com/855743?utm_source=rss&utm_medium=rss&utm_campaign=", 
  "description": "物联网时代下，医疗器械也不安全，医生是时候要化身黑客了。<p>#欢迎关注爱范儿官方微信公众号：爱范儿（微信号：ifanr），更多精彩内容第一时间为您奉上。</p><p>\n<a href=\"http://www.ifanr.com\">爱范儿</a> |\n<a href=\"http://www.ifanr.com/855743\">原文链接</a> ·\n<a href=\"http://www.ifanr.com/855743#comments\">查看评论</a> ·\n<a href=\"http://www.weibo.com/ifanr\">新浪微博</a>\n</p>\n\n<br />\n<div style=\"text-align: center; border-top: 1px dotted #ccc;\">\n</div>", 
  "title": "医生很忙，除了行医，还得学习如何防黑客"
 }, 
 {
  "date": "Sat, 17 Jun 2017 11:30:05 +0000", 
  "link": "http://www.ifanr.com/854644?utm_source=rss&utm_medium=rss&utm_campaign=", 
  "description": "它要帮助员工养成好习惯。<p>#欢迎关注爱范儿官方微信公众号：爱范儿（微信号：ifanr），更多精彩内容第一时间为您奉上。</p><p>\n<a href=\"http://www.ifanr.com\">爱范儿</a> |\n<a href=\"http://www.ifanr.com/854644\">原文链接</a> ·\n<a href=\"http://www.ifanr.com/854644#comments\">查看评论</a> ·\n<a href=\"http://www.weibo.com/ifanr\">新浪微博</a>\n</p>\n\n<br />\n<div style=\"text-align: center; border-top: 1px dotted #ccc;\">\n</div>", 
  "title": "Live OS：Herman Miller 开始制造智能椅子了？"
 }, 
 {
  "date": "Sat, 17 Jun 2017 10:05:56 +0000", 
  "link": "http://www.ifanr.com/855112?utm_source=rss&utm_medium=rss&utm_campaign=", 
  "description": "在 AI 眼里，数学题难道比围棋还难？<p>#欢迎关注爱范儿官方微信公众号：爱范儿（微信号：ifanr），更多精彩内容第一时间为您奉上。</p><p>\n<a href=\"http://www.ifanr.com\">爱范儿</a> |\n<a href=\"http://www.ifanr.com/855112\">原文链接</a> ·\n<a href=\"http://www.ifanr.com/855112#comments\">查看评论</a> ·\n<a href=\"http://www.weibo.com/ifanr\">新浪微博</a>\n</p>\n\n<br />\n<div style=\"text-align: center; border-top: 1px dotted #ccc;\">\n</div>", 
  "title": "现在的 AI 就像娃：玩得转游戏却搞不定数学"
 }, 
 {
  "date": "Sat, 17 Jun 2017 09:46:40 +0000", 
  "link": "http://www.ifanr.com/855689?utm_source=rss&utm_medium=rss&utm_campaign=", 
  "description": "除了一直寄予厚望的生鲜商超之外，亚马逊的「新零售」梦显然有更大的想象空间。<p>#欢迎关注爱范儿官方微信公众号：爱范儿（微信号：ifanr），更多精彩内容第一时间为您奉上。</p><p>\n<a href=\"http://www.ifanr.com\">爱范儿</a> |\n<a href=\"http://www.ifanr.com/855689\">原文链接</a> ·\n<a href=\"http://www.ifanr.com/855689#comments\">查看评论</a> ·\n<a href=\"http://www.weibo.com/ifanr\">新浪微博</a>\n</p>\n\n<br />\n<div style=\"text-align: center; border-top: 1px dotted #ccc;\">\n</div>", 
  "title": "137 亿美元拿下乔布斯最爱的超市，亚马逊到底要干什么？"
 }, 
 {
  "date": "Fri, 16 Jun 2017 15:53:20 +0000", 
  "link": "http://www.ifanr.com/854654?utm_source=rss&utm_medium=rss&utm_campaign=", 
  "description": "空巢青年难道就是没朋友、拒绝社交的死宅么？好像并不是。<p>#欢迎关注爱范儿官方微信公众号：爱范儿（微信号：ifanr），更多精彩内容第一时间为您奉上。</p><p>\n<a href=\"http://www.ifanr.com\">爱范儿</a> |\n<a href=\"http://www.ifanr.com/854654\">原文链接</a> ·\n<a href=\"http://www.ifanr.com/854654#comments\">查看评论</a> ·\n<a href=\"http://www.weibo.com/ifanr\">新浪微博</a>\n</p>\n\n<br />\n<div style=\"text-align: center; border-top: 1px dotted #ccc;\">\n</div>", 
  "title": "关爱空巢青年，从酒店的客房面积缩水开始"
 }, 
 {
  "date": "Fri, 16 Jun 2017 14:45:06 +0000", 
  "link": "http://www.ifanr.com/855110?utm_source=rss&utm_medium=rss&utm_campaign=", 
  "description": "若你喜欢怪人，其实我很美。<p>#欢迎关注爱范儿官方微信公众号：爱范儿（微信号：ifanr），更多精彩内容第一时间为您奉上。</p><p>\n<a href=\"http://www.ifanr.com\">爱范儿</a> |\n<a href=\"http://www.ifanr.com/855110\">原文链接</a> ·\n<a href=\"http://www.ifanr.com/855110#comments\">查看评论</a> ·\n<a href=\"http://www.weibo.com/ifanr\">新浪微博</a>\n</p>\n\n<br />\n<div style=\"text-align: center; border-top: 1px dotted #ccc;\">\n</div>", 
  "title": "软糖的一万种死法，这家公司的脑洞炸裂天际"
 }, 
 {
  "date": "Fri, 16 Jun 2017 13:23:56 +0000", 
  "link": "http://www.ifanr.com/855104?utm_source=rss&utm_medium=rss&utm_campaign=", 
  "description": "然而六年时间过去了，《战意》依然还没有上线。<p>#欢迎关注爱范儿官方微信公众号：爱范儿（微信号：ifanr），更多精彩内容第一时间为您奉上。</p><p>\n<a href=\"http://www.ifanr.com\">爱范儿</a> |\n<a href=\"http://www.ifanr.com/855104\">原文链接</a> ·\n<a href=\"http://www.ifanr.com/855104#comments\">查看评论</a> ·\n<a href=\"http://www.weibo.com/ifanr\">新浪微博</a>\n</p>\n\n<br />\n<div style=\"text-align: center; border-top: 1px dotted #ccc;\">\n</div>", 
  "title": "不鸣工作室王希：被丁磊「藏」了六年，在这个手游时代做了端游《战意》"
 }, 
 {
  "date": "Fri, 16 Jun 2017 12:05:12 +0000", 
  "link": "http://www.ifanr.com/855229?utm_source=rss&utm_medium=rss&utm_campaign=", 
  "description": "互联网将逐渐优化繁琐和落后的传统签证办理流程，而阿里所做的还是第一步。<p>#欢迎关注爱范儿官方微信公众号：爱范儿（微信号：ifanr），更多精彩内容第一时间为您奉上。</p><p>\n<a href=\"http://www.ifanr.com\">爱范儿</a> |\n<a href=\"http://www.ifanr.com/855229\">原文链接</a> ·\n<a href=\"http://www.ifanr.com/855229#comments\">查看评论</a> ·\n<a href=\"http://www.weibo.com/ifanr\">新浪微博</a>\n</p>\n\n<br />\n<div style=\"text-align: center; border-top: 1px dotted #ccc;\">\n</div>", 
  "title": "飞猪推出卢森堡在线签证中心，以后办签证不用跑断腿了？"
 }, 
 {
  "date": "Fri, 16 Jun 2017 10:35:24 +0000", 
  "link": "http://www.ifanr.com/855250?utm_source=rss&utm_medium=rss&utm_campaign=", 
  "description": "有一个车标，它比三环多一环，它比五环少一环，请问它象征啥？<p>#欢迎关注爱范儿官方微信公众号：爱范儿（微信号：ifanr），更多精彩内容第一时间为您奉上。</p><p>\n<a href=\"http://www.ifanr.com\">爱范儿</a> |\n<a href=\"http://www.ifanr.com/855250\">原文链接</a> ·\n<a href=\"http://www.ifanr.com/855250#comments\">查看评论</a> ·\n<a href=\"http://www.weibo.com/ifanr\">新浪微博</a>\n</p>\n\n<br />\n<div style=\"text-align: center; border-top: 1px dotted #ccc;\">\n</div>", 
  "title": "奥迪：差点变成五环不说，它还被国际奥委会起诉过 | 车标史"
 }, 
 {
  "date": "Fri, 16 Jun 2017 10:20:36 +0000", 
  "link": "http://www.ifanr.com/854793?utm_source=rss&utm_medium=rss&utm_campaign=", 
  "description": "当国产手机品牌旗下的专利可以保证他们在美国即使遭遇专利战也能得到一个可以承受的结果时，国产大牌们可能就真要成为国际大牌了。<p>#欢迎关注爱范儿官方微信公众号：爱范儿（微信号：ifanr），更多精彩内容第一时间为您奉上。</p><p>\n<a href=\"http://www.ifanr.com\">爱范儿</a> |\n<a href=\"http://www.ifanr.com/854793\">原文链接</a> ·\n<a href=\"http://www.ifanr.com/854793#comments\">查看评论</a> ·\n<a href=\"http://www.weibo.com/ifanr\">新浪微博</a>\n</p>\n\n<br />\n<div style=\"text-align: center; border-top: 1px dotted #ccc;\">\n</div>", 
  "title": "连华为都遇到了麻烦，国产手机「走出去」真难"
 }, 
 {
  "date": "Fri, 16 Jun 2017 09:37:03 +0000", 
  "link": "http://www.ifanr.com/855087?utm_source=rss&utm_medium=rss&utm_campaign=", 
  "description": "真·土豪的世界里，有钱想花都要先掏邀请函的。<p>#欢迎关注爱范儿官方微信公众号：爱范儿（微信号：ifanr），更多精彩内容第一时间为您奉上。</p><p>\n<a href=\"http://www.ifanr.com\">爱范儿</a> |\n<a href=\"http://www.ifanr.com/855087\">原文链接</a> ·\n<a href=\"http://www.ifanr.com/855087#comments\">查看评论</a> ·\n<a href=\"http://www.weibo.com/ifanr\">新浪微博</a>\n</p>\n\n<br />\n<div style=\"text-align: center; border-top: 1px dotted #ccc;\">\n</div>", 
  "title": "阿斯顿·马丁神车私下发布，还请来女网名将小威“当车模”"
 }, 
 {
  "date": "Fri, 16 Jun 2017 09:21:45 +0000", 
  "link": "http://www.ifanr.com/855215?utm_source=rss&utm_medium=rss&utm_campaign=", 
  "description": "在以健康、健美为潮流的今天，糖果的生意是越来越不好做了。<p>#欢迎关注爱范儿官方微信公众号：爱范儿（微信号：ifanr），更多精彩内容第一时间为您奉上。</p><p>\n<a href=\"http://www.ifanr.com\">爱范儿</a> |\n<a href=\"http://www.ifanr.com/855215\">原文链接</a> ·\n<a href=\"http://www.ifanr.com/855215#comments\">查看评论</a> ·\n<a href=\"http://www.weibo.com/ifanr\">新浪微博</a>\n</p>\n\n<br />\n<div style=\"text-align: center; border-top: 1px dotted #ccc;\">\n</div>", 
  "title": "为了让世界上少点胖子，雀巢决定把美国的糖果业务卖了"
 }, 
 {
  "date": "Fri, 16 Jun 2017 09:09:07 +0000", 
  "link": "http://www.ifanr.com/854862?utm_source=rss&utm_medium=rss&utm_campaign=", 
  "description": "终于，终于，终于把续航和对焦给改了！<p>#欢迎关注爱范儿官方微信公众号：爱范儿（微信号：ifanr），更多精彩内容第一时间为您奉上。</p><p>\n<a href=\"http://www.ifanr.com\">爱范儿</a> |\n<a href=\"http://www.ifanr.com/854862\">原文链接</a> ·\n<a href=\"http://www.ifanr.com/854862#comments\">查看评论</a> ·\n<a href=\"http://www.weibo.com/ifanr\">新浪微博</a>\n</p>\n\n<br />\n<div style=\"text-align: center; border-top: 1px dotted #ccc;\">\n</div>", 
  "title": "索尼 α7 iii 要来了，它将是一款“青春版 α9”"
 }, 
 {
  "date": "Fri, 16 Jun 2017 09:03:39 +0000", 
  "link": "http://www.ifanr.com/854856?utm_source=rss&utm_medium=rss&utm_campaign=", 
  "description": "乔布斯的遗产 100 年不许变，库克的创新能力又被问了好几遍。<p>#欢迎关注爱范儿官方微信公众号：爱范儿（微信号：ifanr），更多精彩内容第一时间为您奉上。</p><p>\n<a href=\"http://www.ifanr.com\">爱范儿</a> |\n<a href=\"http://www.ifanr.com/854856\">原文链接</a> ·\n<a href=\"http://www.ifanr.com/854856#comments\">查看评论</a> ·\n<a href=\"http://www.weibo.com/ifanr\">新浪微博</a>\n</p>\n\n<br />\n<div style=\"text-align: center; border-top: 1px dotted #ccc;\">\n</div>", 
  "title": "库克专访：你能想到记者的提问，却可能猜不到库克口中的答案"
 }
]