[
 {
  "date": "Tue, 09 Aug 2016 09:37:56 +0000", 
  "link": "http://www.ifanr.com/699039?utm_source=rss&utm_medium=rss&utm_campaign=", 
  "description": "“我在 2010 年时设计过一个概念手机“Line Phone”，项目的演示视频在优酷、Youtube上一个月内产生了近 400 万点击量。”<p>#欢迎关注爱范儿认证微信公众号：AppSolution（微信号：appsolution），发现新酷精华应用。</p><img border=\"0\" src=\"http://ifanr.feedsportal.com/c/33866/f/642084/s/699039/mf.gif\" /><br /><br /><a href=\"http://da.feedsportal.com/r/144540365956/u/362/f/642084/c/33866/s/699039/a2.htm\"><img border=\"0\" src=\"http://da.feedsportal.com/r/144540365956/u/362/f/642084/c/33866/s/699039/a2.img\" /></a><img border=\"0\" height=\"1\" src=\"http://pi.feedsportal.com/r/144540365956/u/362/f/642084/c/33866/s/699039/a2t.img\" width=\"1\" /><a href=\"http://a.app.qq.com/o/simple.jsp?pkgname=com.ifanr.activitys\">\n                    <img src=\"http://images.ifanr.cn/wp-content/uploads/2016/04/rss.jpg\" />\n                </a><p>\n<a href=\"http://www.ifanr.com\">爱范儿</a> |\n<a href=\"http://www.ifanr.com/699039\">原文链接</a> ·\n<a href=\"http://www.ifanr.com/699039#comments\">查看评论</a> ·\n<a href=\"http://www.weibo.com/ifanr\">新浪微博</a>\n</p>\n\n<br />\n<div style=\"text-align: center; border-top: 1px dotted #ccc;\">\n</div>", 
  "title": "这个曾经因为一个视频轰动国外科技圈的创业者，现在要让人用极短的时间收集好资料"
 }, 
 {
  "date": "Tue, 09 Aug 2016 09:37:56 +0000", 
  "link": "http://www.ifanr.com/699043?utm_source=rss&utm_medium=rss&utm_campaign=", 
  "description": "爱范儿还在试验自定义表情数量上限中....快去加表情包吧<p>#欢迎关注爱范儿认证微信公众号：AppSolution（微信号：appsolution），发现新酷精华应用。</p><img border=\"0\" src=\"http://ifanr.feedsportal.com/c/33866/f/642084/s/699043/mf.gif\" /><br /><br /><a href=\"http://da.feedsportal.com/r/144540365956/u/362/f/642084/c/33866/s/699043/a2.htm\"><img border=\"0\" src=\"http://da.feedsportal.com/r/144540365956/u/362/f/642084/c/33866/s/699043/a2.img\" /></a><img border=\"0\" height=\"1\" src=\"http://pi.feedsportal.com/r/144540365956/u/362/f/642084/c/33866/s/699043/a2t.img\" width=\"1\" /><a href=\"http://a.app.qq.com/o/simple.jsp?pkgname=com.ifanr.activitys\">\n                    <img src=\"http://images.ifanr.cn/wp-content/uploads/2016/04/rss.jpg\" />\n                </a><p>\n<a href=\"http://www.ifanr.com\">爱范儿</a> |\n<a href=\"http://www.ifanr.com/699043\">原文链接</a> ·\n<a href=\"http://www.ifanr.com/699043#comments\">查看评论</a> ·\n<a href=\"http://www.weibo.com/ifanr\">新浪微博</a>\n</p>\n\n<br />\n<div style=\"text-align: center; border-top: 1px dotted #ccc;\">\n</div>", 
  "title": "表情控福音，微信解锁自定义表情 150 数量限制！"
 }
]